sobol_seq/__init__.py
sobol_seq/sobol_seq-not_tested.py
sobol_seq/sobol_seq.py
sobol_seq-0.2.0.dist-info/METADATA
sobol_seq-0.2.0.dist-info/WHEEL
sobol_seq-0.2.0.dist-info/license.txt
sobol_seq-0.2.0.dist-info/top_level.txt
sobol_seq-0.2.0.dist-info/RECORD
